<?xml version="1.0" encoding="UTF-8" ?><xml><records><record><database name="Library.enl" path="D:\Documents\Cours\BOOKS\R book\Library.enl">Library.enl</database><source-app name="EndNote" version="17.0">EndNote</source-app><rec-number>13</rec-number><foreign-keys><key app="EN" db-id="9wwrprasypew53eex2m5wrsydwaa0e5wparw">13</key></foreign-keys><ref-type name="Journal Article">17</ref-type><contributors><authors><author><style face="normal" font="default" size="100%">Anscombe, F. J.</style></author></authors></contributors><titles><title><style face="normal" font="default" size="100%"> Graphs in Statistical Analysis</style></title><secondary-title><style face="normal" font="default" size="100%">The American Statistician</style></secondary-title></titles><periodical><full-title><style face="normal" font="default" size="100%">The American Statistician</style></full-title></periodical><pages><style face="normal" font="default" size="100%">17-21</style></pages><volume><style face="normal" font="default" size="100%">27</style></volume><number><style face="normal" font="default" size="100%">1</style></number><dates><year><style face="normal" font="default" size="100%">1973</style></year></dates><urls></urls></record><record><database name="Library.enl" path="D:\Documents\Cours\BOOKS\R book\Library.enl">Library.enl</database><source-app name="EndNote" version="17.0">EndNote</source-app><rec-number>4</rec-number><foreign-keys><key app="EN" db-id="9wwrprasypew53eex2m5wrsydwaa0e5wparw">4</key></foreign-keys><ref-type name="Journal Article">17</ref-type><contributors><authors><author><style face="normal" font="default" size="100%">Chatellier, G.</style></author><author><style face="normal" font="default" size="100%">Durieux, P.</style></author></authors></contributors><titles><title><style face="normal" font="default" size="100%">Moyenne, médiane, et leurs indices de dispersion : quand les utiliser et comment les présenter dans un article scientifique ?</style></title><secondary-title><style face="normal" font="default" size="100%">Rev Mal Respir</style></secondary-title></titles><periodical><full-title><style face="normal" font="default" size="100%">Rev Mal Respir</style></full-title></periodical><pages><style face="normal" font="default" size="100%">421-424</style></pages><volume><style face="normal" font="default" size="100%">20</style></volume><number><style face="normal" font="default" size="100%">3</style></number><dates><year><style face="normal" font="default" size="100%">2003</style></year></dates><urls></urls><electronic-resource-num><style face="normal" font="default" size="100%">RMR-06-2003-20-3-0761-8425-101019-ART17</style></electronic-resource-num></record><record><database name="Library.enl" path="D:\Documents\Cours\BOOKS\R book\Library.enl">Library.enl</database><source-app name="EndNote" version="17.0">EndNote</source-app><rec-number>7</rec-number><foreign-keys><key app="EN" db-id="9wwrprasypew53eex2m5wrsydwaa0e5wparw">7</key></foreign-keys><ref-type name="Journal Article">17</ref-type><contributors><authors><author><style face="normal" font="default" size="100%">Dart, T.</style></author><author><style face="normal" font="default" size="100%">Chatellier, G.</style></author></authors></contributors><titles><title><style face="normal" font="default" size="100%">Comment décrire la distribution d&apos;une variable ?</style></title><secondary-title><style face="normal" font="default" size="100%">Rev Mal Respir</style></secondary-title></titles><periodical><full-title><style face="normal" font="default" size="100%">Rev Mal Respir</style></full-title></periodical><pages><style face="normal" font="default" size="100%">946-951</style></pages><volume><style face="normal" font="default" size="100%">20</style></volume><number><style face="normal" font="default" size="100%">6</style></number><dates><year><style face="normal" font="default" size="100%">2003</style></year></dates><urls></urls><electronic-resource-num><style face="normal" font="default" size="100%">RMR-12-2003-20-6-0761-8425-101019-ART19</style></electronic-resource-num></record><record><database name="Library.enl" path="D:\Documents\Cours\BOOKS\R book\Library.enl">Library.enl</database><source-app name="EndNote" version="17.0">EndNote</source-app><rec-number>10</rec-number><foreign-keys><key app="EN" db-id="9wwrprasypew53eex2m5wrsydwaa0e5wparw">10</key></foreign-keys><ref-type name="Journal Article">17</ref-type><contributors><authors><author><style face="normal" font="default" size="100%">Gonzales, V. A.</style></author><author><style face="normal" font="default" size="100%">Ottenbacher, K. J.</style></author></authors></contributors><auth-address><style face="normal" font="default" size="100%">School of Allied Health Sciences, University of Texas Medical Branch at Galveston, 77555-1028, USA.</style></auth-address><titles><title><style face="normal" font="default" size="100%">Measures of central tendency in rehabilitation research: what do they mean?</style></title><secondary-title><style face="normal" font="default" size="100%">Am J Phys Med Rehabil</style></secondary-title><alt-title><style face="normal" font="default" size="100%">American journal of physical medicine &amp; rehabilitation</style></alt-title></titles><periodical><full-title><style face="normal" font="default" size="100%">Am J Phys Med Rehabil</style></full-title><abbr-1><style face="normal" font="default" size="100%">American journal of physical medicine &amp; rehabilitation</style></abbr-1></periodical><alt-periodical><full-title><style face="normal" font="default" size="100%">Am J Phys Med Rehabil</style></full-title><abbr-1><style face="normal" font="default" size="100%">American journal of physical medicine &amp; rehabilitation</style></abbr-1></alt-periodical><pages><style face="normal" font="default" size="100%">141-6</style></pages><volume><style face="normal" font="default" size="100%">80</style></volume><number><style face="normal" font="default" size="100%">2</style></number><edition><style face="normal" font="default" size="100%">2001/02/24</style></edition><keywords><keyword><style face="normal" font="default" size="100%">*Data Interpretation, Statistical</style></keyword><keyword><style face="normal" font="default" size="100%">Humans</style></keyword><keyword><style face="normal" font="default" size="100%">*Rehabilitation</style></keyword></keywords><dates><year><style face="normal" font="default" size="100%">2001</style></year><pub-dates><date><style face="normal" font="default" size="100%">Feb</style></date></pub-dates></dates><isbn><style face="normal" font="default" size="100%">0894-9115 (Print)&#xD;0894-9115</style></isbn><accession-num><style face="normal" font="default" size="100%">11212015</style></accession-num><abstract><style face="normal" font="default" size="100%">Measures of central tendency including the mean, median, and mode are commonly reported in rehabilitation research. It is believed that the relationship among the mean, median, and mode changes in a specific way when the distribution being analyzed is skewed. A number of widely used textbooks were reviewed to determine how the relationship among the mean, median, and mode is presented in the health sciences and rehabilitation literature. We report a potential misinterpretation of the relationship between measures of central tendency that was identified in several research and statistical textbooks on the subject of rehabilitation. The misinterpretation involves measures of central tendency derived from skewed unimodal sample distributions. The reviewed textbooks state or imply that in asymmetrical distributions, the median is always located between the mode and mean. An example is presented illustrating the fallacy of this assumption. The mean and median will always be to the right of the mode in a positively skewed unimodal distribution and to the left of the mode in a negatively skewed distribution; the order of the mean and median is impossible to predict or generalize. The assumption that the median always falls between the mode and mean in the calculation of coefficients of skewness has implications for the interpretation of exploratory and confirmatory data analysis in rehabilitation research.</style></abstract><notes><style face="normal" font="default" size="100%">Gonzales, V A&#xD;Ottenbacher, K J&#xD;H133P990001/PHS HHS/United States&#xD;Journal Article&#xD;Research Support, U.S. Gov&apos;t, P.H.S.&#xD;United States&#xD;Am J Phys Med Rehabil. 2001 Feb;80(2):141-6. doi: 10.1097/00002060-200102000-00014.</style></notes><urls></urls><electronic-resource-num><style face="normal" font="default" size="100%">10.1097/00002060-200102000-00014</style></electronic-resource-num><remote-database-provider><style face="normal" font="default" size="100%">Nlm</style></remote-database-provider><language><style face="normal" font="default" size="100%">eng</style></language></record><record><database name="Library.enl" path="D:\Documents\Cours\BOOKS\R book\Library.enl">Library.enl</database><source-app name="EndNote" version="17.0">EndNote</source-app><rec-number>6</rec-number><foreign-keys><key app="EN" db-id="9wwrprasypew53eex2m5wrsydwaa0e5wparw">6</key></foreign-keys><ref-type name="Journal Article">17</ref-type><contributors><authors><author><style face="normal" font="default" size="100%">Grenier, E.</style></author></authors></contributors><titles><title><style face="normal" font="default" size="100%">Quelle est la « bonne » formule de l’écart-type ?</style></title><secondary-title><style face="normal" font="default" size="100%">Revue MODULAD</style></secondary-title></titles><periodical><full-title><style face="normal" font="default" size="100%">Revue MODULAD</style></full-title></periodical><pages><style face="normal" font="default" size="100%">102-105</style></pages><volume><style face="normal" font="default" size="100%">37</style></volume><dates><year><style face="normal" font="default" size="100%">2007</style></year></dates><urls></urls></record><record><database name="Library.enl" path="D:\Documents\Cours\BOOKS\R book\Library.enl">Library.enl</database><source-app name="EndNote" version="17.0">EndNote</source-app><rec-number>14</rec-number><foreign-keys><key app="EN" db-id="9wwrprasypew53eex2m5wrsydwaa0e5wparw">14</key></foreign-keys><ref-type name="Journal Article">17</ref-type><contributors><authors><author><style face="normal" font="default" size="100%">Hopkins, W. G.</style></author><author><style face="normal" font="default" size="100%">Marshall, S. W.</style></author><author><style face="normal" font="default" size="100%">Batterham, A. M.</style></author><author><style face="normal" font="default" size="100%">Hanin, J.</style></author></authors></contributors><auth-address><style face="normal" font="default" size="100%">Institute of Sport and Recreation Research, AUT University, Auckland, New Zealand. will@clear.net.nz</style></auth-address><titles><title><style face="normal" font="default" size="100%">Progressive statistics for studies in sports medicine and exercise science</style></title><secondary-title><style face="normal" font="default" size="100%">Med Sci Sports Exerc</style></secondary-title><alt-title><style face="normal" font="default" size="100%">Medicine and science in sports and exercise</style></alt-title></titles><periodical><full-title><style face="normal" font="default" size="100%">Med Sci Sports Exerc</style></full-title><abbr-1><style face="normal" font="default" size="100%">Medicine and science in sports and exercise</style></abbr-1></periodical><alt-periodical><full-title><style face="normal" font="default" size="100%">Med Sci Sports Exerc</style></full-title><abbr-1><style face="normal" font="default" size="100%">Medicine and science in sports and exercise</style></abbr-1></alt-periodical><pages><style face="normal" font="default" size="100%">3-13</style></pages><volume><style face="normal" font="default" size="100%">41</style></volume><number><style face="normal" font="default" size="100%">1</style></number><keywords><keyword><style face="normal" font="default" size="100%">*Biomedical Research</style></keyword><keyword><style face="normal" font="default" size="100%">*Data Interpretation, Statistical</style></keyword><keyword><style face="normal" font="default" size="100%">Exercise/*physiology</style></keyword><keyword><style face="normal" font="default" size="100%">Humans</style></keyword><keyword><style face="normal" font="default" size="100%">*Research Design</style></keyword><keyword><style face="normal" font="default" size="100%">Sample Size</style></keyword><keyword><style face="normal" font="default" size="100%">*Sports Medicine</style></keyword></keywords><dates><year><style face="normal" font="default" size="100%">2009</style></year><pub-dates><date><style face="normal" font="default" size="100%">Jan</style></date></pub-dates></dates><isbn><style face="normal" font="default" size="100%">1530-0315 (Electronic)&#xD;0195-9131 (Linking)</style></isbn><accession-num><style face="normal" font="default" size="100%">19092709</style></accession-num><abstract><style face="normal" font="default" size="100%">Statistical guidelines and expert statements are now available to assist in the analysis and reporting of studies in some biomedical disciplines. We present here a more progressive resource for sample-based studies, meta-analyses, and case studies in sports medicine and exercise science. We offer forthright advice on the following controversial or novel issues: using precision of estimation for inferences about population effects in preference to null-hypothesis testing, which is inadequate for assessing clinical or practical importance; justifying sample size via acceptable precision or confidence for clinical decisions rather than via adequate power for statistical significance; showing SD rather than SEM, to better communicate the magnitude of differences in means and nonuniformity of error; avoiding purely nonparametric analyses, which cannot provide inferences about magnitude and are unnecessary; using regression statistics in validity studies, in preference to the impractical and biased limits of agreement; making greater use of qualitative methods to enrich sample-based quantitative projects; and seeking ethics approval for public access to the depersonalized raw data of a study, to address the need for more scrutiny of research and better meta-analyses. Advice on less contentious issues includes the following: using covariates in linear models to adjust for confounders, to account for individual differences, and to identify potential mechanisms of an effect; using log transformation to deal with nonuniformity of effects and error; identifying and deleting outliers; presenting descriptive, effect, and inferential statistics in appropriate formats; and contending with bias arising from problems with sampling, assignment, blinding, measurement error, and researchers&apos; prejudices. This article should advance the field by stimulating debate, promoting innovative approaches, and serving as a useful checklist for authors, reviewers, and editors.</style></abstract><notes><style face="normal" font="default" size="100%">Hopkins, William G&#xD;Marshall, Stephen W&#xD;Batterham, Alan M&#xD;Hanin, Juri&#xD;eng&#xD;Review&#xD;2008/12/19 09:00&#xD;Med Sci Sports Exerc. 2009 Jan;41(1):3-13. doi: 10.1249/MSS.0b013e31818cb278.</style></notes><urls><related-urls><url><style face="normal" font="default" size="100%">http://www.ncbi.nlm.nih.gov/pubmed/19092709</style></url></related-urls></urls><electronic-resource-num><style face="normal" font="default" size="100%">10.1249/MSS.0b013e31818cb278</style></electronic-resource-num></record><record><database name="Library.enl" path="D:\Documents\Cours\BOOKS\R book\Library.enl">Library.enl</database><source-app name="EndNote" version="17.0">EndNote</source-app><rec-number>9</rec-number><foreign-keys><key app="EN" db-id="9wwrprasypew53eex2m5wrsydwaa0e5wparw">9</key></foreign-keys><ref-type name="Journal Article">17</ref-type><contributors><authors><author><style face="normal" font="default" size="100%">Joanes, D. N.</style></author><author><style face="normal" font="default" size="100%">Gill, C. A.</style></author></authors></contributors><titles><title><style face="normal" font="default" size="100%">Comparing measures of sample skewness and kurtosis</style></title><secondary-title><style face="normal" font="default" size="100%">The Statistician</style></secondary-title></titles><periodical><full-title><style face="normal" font="default" size="100%">The Statistician</style></full-title></periodical><pages><style face="normal" font="default" size="100%">183-189</style></pages><volume><style face="normal" font="default" size="100%">47</style></volume><number><style face="normal" font="default" size="100%">Part 1</style></number><dates><year><style face="normal" font="default" size="100%">1998</style></year></dates><urls></urls><electronic-resource-num><style face="normal" font="default" size="100%">10.1111/1467-9884.00122</style></electronic-resource-num></record><record><database name="Library.enl" path="D:\Documents\Cours\BOOKS\R book\Library.enl">Library.enl</database><source-app name="EndNote" version="17.0">EndNote</source-app><rec-number>1</rec-number><foreign-keys><key app="EN" db-id="9wwrprasypew53eex2m5wrsydwaa0e5wparw">1</key></foreign-keys><ref-type name="Journal Article">17</ref-type><contributors><authors><author><style face="normal" font="default" size="100%">Labreuche, Julien</style></author></authors></contributors><titles><title><style face="normal" font="default" size="100%">Les différents types de variables, leurs représentations graphiques et paramètres descriptifs</style></title><secondary-title><style face="normal" font="default" size="100%">Sang Thrombose Vaisseaux</style></secondary-title></titles><periodical><full-title><style face="normal" font="default" size="100%">Sang Thrombose Vaisseaux</style></full-title></periodical><pages><style face="normal" font="default" size="100%">536-543</style></pages><volume><style face="normal" font="default" size="100%">22</style></volume><number><style face="normal" font="default" size="100%">10</style></number><dates><year><style face="normal" font="default" size="100%">2010</style></year><pub-dates><date><style face="normal" font="default" size="100%">12/01</style></date></pub-dates></dates><isbn><style face="normal" font="default" size="100%">0999-7385</style></isbn><abstract><style face="normal" font="default" size="100%">Quel que soit le phénomène étudié, on est amené à collecter et analyser un ensemble de données communément appelé en statistique « ensemble de variables ». Il existe principalement deux groupes de variables : les variables quantitatives et les variables qualitatives, qui peuvent être subdivisés en plusieurs sous-groupes. La reconnaissance des différents types de variables est la première étape d&apos;une analyse de données car le choix des outils et méthodes statistiques à utiliser en dépend. Cette note aborde les différents types de variables que l&apos;on peut rencontrer en recherche médicale. Elle décrit également les principaux graphiques (histogramme, boîte à moustaches, diagramme en bâtons, diagramme circulaire) et paramètres descriptifs (effectif, fréquence, moyenne, écart type, médiane, étendue interquartile) utilisés pour résumer l&apos;information collectée.</style></abstract><urls></urls><electronic-resource-num><style face="normal" font="default" size="100%">10.1684/stv.2010.0541</style></electronic-resource-num></record><record><database name="Library.enl" path="D:\Documents\Cours\BOOKS\R book\Library.enl">Library.enl</database><source-app name="EndNote" version="17.0">EndNote</source-app><rec-number>5</rec-number><foreign-keys><key app="EN" db-id="9wwrprasypew53eex2m5wrsydwaa0e5wparw">5</key></foreign-keys><ref-type name="Book">6</ref-type><contributors><authors><author><style face="normal" font="default" size="100%">Navarro, D.</style></author></authors></contributors><titles><title><style face="normal" font="default" size="100%">Learning statistics with R</style></title></titles><pages><style face="normal" font="default" size="100%">599</style></pages><dates><year><style face="normal" font="default" size="100%">2018</style></year></dates><pub-location><style face="normal" font="default" size="100%">Publié en ligne</style></pub-location><publisher><style face="normal" font="default" size="100%">UNSW Computational Cognitive Science</style></publisher><urls></urls></record><record><database name="Library.enl" path="D:\Documents\Cours\BOOKS\R book\Library.enl">Library.enl</database><source-app name="EndNote" version="17.0">EndNote</source-app><rec-number>11</rec-number><foreign-keys><key app="EN" db-id="9wwrprasypew53eex2m5wrsydwaa0e5wparw">11</key></foreign-keys><ref-type name="Journal Article">17</ref-type><contributors><authors><author><style face="normal" font="default" size="100%">Rousselet, G. A.</style></author><author><style face="normal" font="default" size="100%">Wilcox, R. R.</style></author></authors></contributors><titles><title><style face="normal" font="default" size="100%">Reaction times and other skewed distributions: problems with the mean and the median</style></title><secondary-title><style face="normal" font="default" size="100%">Meta-Psychology</style></secondary-title></titles><periodical><full-title><style face="normal" font="default" size="100%">Meta-Psychology</style></full-title></periodical><pages><style face="normal" font="default" size="100%">1-39</style></pages><volume><style face="normal" font="default" size="100%">4</style></volume><dates><year><style face="normal" font="default" size="100%">2020</style></year></dates><urls></urls><electronic-resource-num><style face="normal" font="default" size="100%">10.15626/MP.2019.1630</style></electronic-resource-num></record><record><database name="Library.enl" path="D:\Documents\Cours\BOOKS\R book\Library.enl">Library.enl</database><source-app name="EndNote" version="17.0">EndNote</source-app><rec-number>3</rec-number><foreign-keys><key app="EN" db-id="9wwrprasypew53eex2m5wrsydwaa0e5wparw">3</key></foreign-keys><ref-type name="Book">6</ref-type><contributors><authors><author><style face="normal" font="default" size="100%">Wickham, H.</style></author></authors></contributors><titles><title><style face="normal" font="default" size="100%">ggplot2</style></title></titles><pages><style face="normal" font="default" size="100%">213</style></pages><edition><style face="normal" font="default" size="100%">2nd</style></edition><dates><year><style face="normal" font="default" size="100%">2016</style></year></dates><pub-location><style face="normal" font="default" size="100%">New York City, NY</style></pub-location><publisher><style face="normal" font="default" size="100%">Springer-Verlag</style></publisher><urls></urls><electronic-resource-num><style face="normal" font="default" size="100%">10.1007/978-0-387-98141-3</style></electronic-resource-num></record><record><database name="Library.enl" path="D:\Documents\Cours\BOOKS\R book\Library.enl">Library.enl</database><source-app name="EndNote" version="17.0">EndNote</source-app><rec-number>2</rec-number><foreign-keys><key app="EN" db-id="9wwrprasypew53eex2m5wrsydwaa0e5wparw">2</key></foreign-keys><ref-type name="Book">6</ref-type><contributors><authors><author><style face="normal" font="default" size="100%">Wickham, H.</style></author><author><style face="normal" font="default" size="100%">Grolemund, G.</style></author></authors></contributors><titles><title><style face="normal" font="default" size="100%">R for Data Science</style></title></titles><pages><style face="normal" font="default" size="100%">492</style></pages><dates><year><style face="normal" font="default" size="100%">2017</style></year></dates><pub-location><style face="normal" font="default" size="100%">Sebastopol, CA</style></pub-location><publisher><style face="normal" font="default" size="100%">O&apos;Reilly</style></publisher><isbn><style face="normal" font="default" size="100%">9781491910399</style></isbn><urls></urls></record><record><database name="Library.enl" path="D:\Documents\Cours\BOOKS\R book\Library.enl">Library.enl</database><source-app name="EndNote" version="17.0">EndNote</source-app><rec-number>12</rec-number><foreign-keys><key app="EN" db-id="9wwrprasypew53eex2m5wrsydwaa0e5wparw">12</key></foreign-keys><ref-type name="Book">6</ref-type><contributors><authors><author><style face="normal" font="default" size="100%">Wilke, C. O.</style></author></authors></contributors><titles><title><style face="normal" font="default" size="100%">Fundamentals of data visualization</style></title></titles><pages><style face="normal" font="default" size="100%">300</style></pages><dates><year><style face="normal" font="default" size="100%">2018</style></year></dates><pub-location><style face="normal" font="default" size="100%">Sebastopol, CA</style></pub-location><publisher><style face="normal" font="default" size="100%">O’Reilly Media, Inc. Retrieved from https://serialmentor.com/dataviz</style></publisher><urls></urls></record></records></xml>